hilbert_quantization/__init__.py
hilbert_quantization/api.py
hilbert_quantization/cli.py
hilbert_quantization/config.py
hilbert_quantization/exceptions.py
hilbert_quantization/interfaces.py
hilbert_quantization/models.py
hilbert_quantization/optimized.py
hilbert_quantization/py.typed
hilbert_quantization/video_api.py
hilbert_quantization/core/__init__.py
hilbert_quantization/core/compressor.py
hilbert_quantization/core/cv_features.py
hilbert_quantization/core/dimension_calculator.py
hilbert_quantization/core/hilbert_mapper.py
hilbert_quantization/core/index_generator.py
hilbert_quantization/core/pipeline.py
hilbert_quantization/core/precomputed_hilbert_index.py
hilbert_quantization/core/search_engine.py
hilbert_quantization/core/streaming_index_builder.py
hilbert_quantization/core/streaming_processor.py
hilbert_quantization/core/video_search.py
hilbert_quantization/core/video_storage.py
hilbert_quantization/rag/__init__.py
hilbert_quantization/rag/api.py
hilbert_quantization/rag/config.py
hilbert_quantization/rag/interfaces.py
hilbert_quantization/rag/models.py
hilbert_quantization/rag/validation.py
hilbert_quantization/rag/document_processing/__init__.py
hilbert_quantization/rag/document_processing/batch_processor.py
hilbert_quantization/rag/document_processing/chunker.py
hilbert_quantization/rag/document_processing/document_validator.py
hilbert_quantization/rag/document_processing/ipfs_integration.py
hilbert_quantization/rag/document_processing/metadata_manager.py
hilbert_quantization/rag/embedding_generation/__init__.py
hilbert_quantization/rag/embedding_generation/compressor.py
hilbert_quantization/rag/embedding_generation/dimension_calculator.py
hilbert_quantization/rag/embedding_generation/generator.py
hilbert_quantization/rag/embedding_generation/hierarchical_index_generator.py
hilbert_quantization/rag/embedding_generation/hilbert_mapper.py
hilbert_quantization/rag/embedding_generation/reconstructor.py
hilbert_quantization/rag/search/__init__.py
hilbert_quantization-1.3.0.dist-info/licenses/LICENSE
hilbert_quantization-1.3.0.dist-info/METADATA
hilbert_quantization-1.3.0.dist-info/WHEEL
hilbert_quantization-1.3.0.dist-info/entry_points.txt
hilbert_quantization-1.3.0.dist-info/top_level.txt
hilbert_quantization-1.3.0.dist-info/RECORD
