Metadata-Version: 2.4
Name: hilbert-quantization
Version: 1.3.0
Summary: Ultra-fast similarity search with Hilbert curve quantization and MPEG-AI compression
Author-email: Tyler Hess <tylerlhess@gmail.com>
Maintainer-email: Tyler Hess <tylerlhess@gmail.com>
License-Expression: MIT
Project-URL: Homepage, https://github.com/tylerlhess/hilbert-quantization
Project-URL: Documentation, https://github.com/tylerlhess/hilbert-quantization#readme
Project-URL: Repository, https://github.com/tylerlhess/hilbert-quantization
Project-URL: Bug Tracker, https://github.com/tylerlhess/hilbert-quantization/issues
Project-URL: Changelog, https://github.com/tylerlhess/hilbert-quantization/blob/main/CHANGELOG.md
Keywords: similarity-search,vector-database,hilbert-curve,quantization,compression,embeddings,nearest-neighbors,machine-learning,ai
Classifier: Development Status :: 4 - Beta
Classifier: Intended Audience :: Developers
Classifier: Intended Audience :: Science/Research
Classifier: Operating System :: OS Independent
Classifier: Programming Language :: Python :: 3
Classifier: Programming Language :: Python :: 3.8
Classifier: Programming Language :: Python :: 3.9
Classifier: Programming Language :: Python :: 3.10
Classifier: Programming Language :: Python :: 3.11
Classifier: Programming Language :: Python :: 3.12
Classifier: Topic :: Scientific/Engineering :: Artificial Intelligence
Classifier: Topic :: Software Development :: Libraries :: Python Modules
Classifier: Topic :: Database :: Database Engines/Servers
Requires-Python: >=3.8
License-File: LICENSE
Requires-Dist: numpy>=1.20.0
Requires-Dist: psutil>=5.8.0
Provides-Extra: dev
Requires-Dist: pytest>=6.0; extra == "dev"
Requires-Dist: pytest-cov>=2.0; extra == "dev"
Requires-Dist: black>=21.0; extra == "dev"
Requires-Dist: flake8>=3.8; extra == "dev"
Requires-Dist: mypy>=0.800; extra == "dev"
Requires-Dist: pre-commit>=2.0; extra == "dev"
Provides-Extra: benchmark
Requires-Dist: matplotlib>=3.3.0; extra == "benchmark"
Requires-Dist: seaborn>=0.11.0; extra == "benchmark"
Requires-Dist: pandas>=1.3.0; extra == "benchmark"
Provides-Extra: gpu
Requires-Dist: cupy-cuda11x>=9.0.0; platform_machine == "x86_64" and extra == "gpu"
Requires-Dist: numba>=0.56.0; extra == "gpu"
Dynamic: license-file
